specimux/__init__.py
specimux/alignment.py
specimux/bloom_filter.py
specimux/cli.py
specimux/constants.py
specimux/converter.py
specimux/core.py
specimux/databases.py
specimux/demultiplex.py
specimux/io_utils.py
specimux/models.py
specimux/multiprocessing_utils.py
specimux/orchestration.py
specimux/specimine.py
specimux/trace.py
specimux/trace_stats.py
specimux/visualize.py
specimux/watch.py
specimux-0.7.0.dist-info/licenses/LICENSE
specimux-0.7.0.dist-info/METADATA
specimux-0.7.0.dist-info/WHEEL
specimux-0.7.0.dist-info/entry_points.txt
specimux-0.7.0.dist-info/top_level.txt
specimux-0.7.0.dist-info/RECORD
