Metadata-Version: 2.4
Name: specimux
Version: 0.7.0
Summary: Dual barcode and primer demultiplexing system for MinION sequenced reads
Author-email: Josh Walker <joshowalker@yahoo.com>
License: BSD 2-Clause License
Project-URL: Homepage, https://github.com/joshuaowalker/specimux
Project-URL: Repository, https://github.com/joshuaowalker/specimux
Project-URL: Issues, https://github.com/joshuaowalker/specimux/issues
Keywords: bioinformatics,demultiplexing,minion,nanopore,sequencing
Classifier: Development Status :: 4 - Beta
Classifier: Intended Audience :: Science/Research
Classifier: Topic :: Scientific/Engineering :: Bio-Informatics
Classifier: Programming Language :: Python :: 3
Classifier: Programming Language :: Python :: 3.10
Classifier: Programming Language :: Python :: 3.11
Classifier: Programming Language :: Python :: 3.12
Classifier: Programming Language :: Python :: 3.13
Requires-Python: >=3.10
License-File: LICENSE
Requires-Dist: edlib>=1.1.2
Requires-Dist: biopython>=1.81
Requires-Dist: pybloomfilter3>=0.7.3
Requires-Dist: cachetools>=5.3.0
Requires-Dist: tqdm>=4.65.0
Requires-Dist: plotly>=5.0.0
Requires-Dist: watchdog>=3.0.0
Provides-Extra: dev
Requires-Dist: pytest>=7.0.0; extra == "dev"
Requires-Dist: pytest-cov>=4.0.0; extra == "dev"
Requires-Dist: black>=23.0.0; extra == "dev"
Requires-Dist: ruff>=0.1.0; extra == "dev"
Provides-Extra: test
Requires-Dist: pytest>=7.0.0; extra == "test"
Requires-Dist: pytest-cov>=4.0.0; extra == "test"
Dynamic: license-file
